[
  {
    "title": "React",
    "imageSrc": "skills/react.svg"
  },
  {
    "title": "Vite",
    "imageSrc": "skills/vite.svg"
  },
  {
    "title": "tailwind",
    "imageSrc": "skills/tailwind.svg"
  },
  {
    "title": "HTML",
    "imageSrc": "skills/html.svg"
  },
  {
    "title": "CSS",
    "imageSrc": "skills/css.svg"
  },
  {
    "title": "JavaScript",
    "imageSrc": "skills/javascript.svg"
  },
  {
    "title": "gatsby",
    "imageSrc": "skills/gatsby.svg"
  },
  {
    "title": "Figma",
    "imageSrc": "skills/figma.svg"
  }
]